saylt/__init__.py
saylt/message.txt
saylt-0.1.8.dist-info/licenses/LICENSE
saylt-0.1.8.dist-info/METADATA
saylt-0.1.8.dist-info/WHEEL
saylt-0.1.8.dist-info/top_level.txt
saylt-0.1.8.dist-info/RECORD
