Metadata-Version: 2.4
Name: saylt
Version: 0.1.8
Summary: A simple demo library that prints text when imported.
Author-email: SAYLT <diego@gmail.com>
License: MIT License
Requires-Python: >=3.7
License-File: LICENSE
Dynamic: license-file
